icingapy.py
icingapy-0.1.2.dist-info/AUTHORS
icingapy-0.1.2.dist-info/LICENSE
icingapy-0.1.2.dist-info/METADATA
icingapy-0.1.2.dist-info/WHEEL
icingapy-0.1.2.dist-info/pbr.json
icingapy-0.1.2.dist-info/top_level.txt
icingapy-0.1.2.dist-info/RECORD
