Metadata-Version: 2.1
Name: icingapy
Version: 0.1.2
Summary: A library for interacting/scrapping Icinga 1 CGI endpoints
Home-page: https://github.com/GenPage/icingapy
Author: Dylan Page
Author-email: genpage@pagefortress.com
License: Apache-2
Keywords: icinga
Platform: UNKNOWN
Classifier: Development Status :: 4 - Beta
Classifier: Programming Language :: Python :: 3
Classifier: License :: OSI Approved :: Apache Software License
Classifier: Operating System :: OS Independent
Classifier: Topic :: Software Development :: Libraries
Classifier: Topic :: System :: Monitoring
Requires-Dist: requests
Requires-Dist: bs4
